ncl_sqlsnippets/__init__.py
ncl_sqlsnippets/sqlsnippets.py
ncl_sqlsnippets-1.3.0.dist-info/LICENSE
ncl_sqlsnippets-1.3.0.dist-info/METADATA
ncl_sqlsnippets-1.3.0.dist-info/WHEEL
ncl_sqlsnippets-1.3.0.dist-info/top_level.txt
ncl_sqlsnippets-1.3.0.dist-info/RECORD
