Metadata-Version: 2.1
Name: ncl_sqlsnippets
Version: 1.3.0
Summary: Module containing standard python functions to interact with the sandpit
Author-email: Jake Kealey <jake.kealey@nhs.net>
Project-URL: Homepage, https://github.com/ncl-icb-analytics/sqlsnippets
Project-URL: Issues, https://github.com/ncl-icb-analytics/sqlsnippets/issues
Classifier: Programming Language :: Python :: 3
Classifier: License :: OSI Approved :: MIT License
Classifier: Operating System :: OS Independent
Requires-Python: >=3.9
License-File: LICENSE
Requires-Dist: pandas >=2.1.4
Requires-Dist: SQLAlchemy >=2.0.5.post1
